bindfiles/__init__.py
bindfiles/api/__init__.py
bindfiles/api/creds.py
bindfiles/api/drive.py
bindfiles/api/mail.py
bindfiles/api/rest_build.py
bindfiles/api/sheet.py
bindfiles/filesync/__init__.py
bindfiles/filesync/engine.py
bindfiles/filesync/interface.py
bindfiles/filesync/schema.py
bindfiles/filesync/settings.py
bindfiles/gclient/drive_v3.py
bindfiles/gclient/gmail_v1.py
bindfiles/gclient/sheets_v4.py
bindfiles/html/__output__.js
bindfiles/html/main.html
bindfiles/tools/file_source.py
bindfiles/tools/funcs.py
bindfiles/tools/machine.py
bindfiles/tools/search_engine.py
bindfiles-0.0.4.dist-info/METADATA
bindfiles-0.0.4.dist-info/WHEEL
bindfiles-0.0.4.dist-info/top_level.txt
bindfiles-0.0.4.dist-info/RECORD
