Metadata-Version: 2.1
Name: bindfiles
Version: 0.0.4
Summary: Google API Helper
Author-email: Christoph Chester Cury <cury.grupos@gmail.com>
License: MIT
Classifier: Programming Language :: Python :: 3
Classifier: License :: OSI Approved :: MIT License
Classifier: Operating System :: OS Independent
Requires-Python: >=3.6
Requires-Dist: google-api-python-client
Requires-Dist: google-auth-httplib2
Requires-Dist: google-auth-oauthlib
Requires-Dist: typing-extensions
Requires-Dist: pytz
Requires-Dist: nbDevTools
Requires-Dist: anywidget
